{"transformations":[{"failures":[],"variableMapping":{},"name":"replaceWittgenstein","transplant":{"sourceCode":"return java.util.Map<K, V>","position":"org.apache.commons.collections4.splitmap.AbstractIterableGetMapDecorator:60","type":"CtReturnImpl"},"type":"adrStmt","transplantationPoint":{"sourceCode":"return java.util.Map<E, org.apache.commons.collections4.bag.AbstractMapBag.MutableInteger>","position":"org.apache.commons.collections4.bag.AbstractMapBag:80","type":"CtReturnImpl"},"status":0},{"failures":[],"variableMapping":{"lastUsedIterator":"currentIterator","currentIterator":"currentIterator"},"name":"add","transplant":{"sourceCode":"java.util.Iterator<? extends E> = java.util.Iterator<? extends E>","position":"org.apache.commons.collections4.iterators.IteratorChain:252","type":"CtAssignmentImpl"},"type":"adrStmt","transplantationPoint":{"sourceCode":"java.util.Iterator<? extends E> = org.apache.commons.collections4.iterators.LazyIteratorChain<E>.nextIterator(++(int))","position":"org.apache.commons.collections4.iterators.LazyIteratorChain:84","type":"CtAssignmentImpl"},"status":0},{"failures":[],"variableMapping":{"curObject":"previousObject","leastObject":"previousObject"},"name":"add","transplant":{"sourceCode":"E = E","position":"org.apache.commons.collections4.iterators.CollatingIterator:369","type":"CtAssignmentImpl"},"type":"adrStmt","transplantationPoint":{"sourceCode":"E = null","position":"org.apache.commons.collections4.iterators.FilterListIterator:243","type":"CtAssignmentImpl"},"status":0},{"failures":[],"variableMapping":{"o":"object"},"name":"add","transplant":{"sourceCode":"if (java.lang.Object == this) {\r\n    return true;\r\n} else if (!(java.lang.Object instanceof java.util.Map.Entry)) {\r\n    return false;\r\n} ","position":"org.apache.commons.collections4.trie.AbstractBitwiseTrie:194","type":"CtIfImpl"},"type":"adrStmt","transplantationPoint":{"sourceCode":"if (java.lang.Object == this) {\r\n    return true;\r\n} ","position":"org.apache.commons.collections4.splitmap.AbstractIterableGetMapDecorator:109","type":"CtIfImpl"},"status":0},{"failures":[],"variableMapping":{},"name":"replaceWittgenstein","transplant":{"sourceCode":"org.apache.commons.collections4.collection.SynchronizedCollection<E>.decorated().clear()","position":"org.apache.commons.collections4.collection.SynchronizedCollection:119","type":"CtInvocationImpl"},"type":"adrStmt","transplantationPoint":{"sourceCode":"org.apache.commons.collections4.list.SetUniqueList<E>.clear()","position":"org.apache.commons.collections4.list.SetUniqueList:266","type":"CtInvocationImpl"},"status":0}],"failedTests":[],"id":100,"status":-2}