{"transformations":[{"failures":[],"variableMapping":{},"name":"replaceWittgenstein","transplant":{"sourceCode":"throw new java.util.NoSuchElementException(\"Iterator contains no elements\")","position":"org.apache.commons.collections4.iterators.AbstractEmptyIterator:41","type":"CtThrowImpl"},"type":"adrStmt","transplantationPoint":{"sourceCode":"throw new java.lang.IllegalStateException((((((((((((((\"Entry.next=null, data[removeIndex]=\" + (org.apache.commons.collections4.map.AbstractHashedMap.HashEntry<K, V>[][int])) + \" previous=\") + org.apache.commons.collections4.map.AbstractHashedMap.HashEntry<K, V>) + \" key=\") + K) + \" value=\") + V) + \" size=\") + (int)) + \" maxSize=\") + (int)) + \" Please check that your keys are immutable, and that you have used synchronization properly.\") + \" If so, then please report this to dev@commons.apache.org as a bug.\"))","position":"org.apache.commons.collections4.map.LRUMap:311","type":"CtThrowImpl"},"status":0},{"failures":[],"variableMapping":{"closure":"iClosure"},"name":"replace","transplant":{"sourceCode":"if (org.apache.commons.collections4.Closure<? super T> == null) {\r\n    throw new java.lang.IllegalArgumentException(\"Closure must not be null\");\r\n} ","position":"org.apache.commons.collections4.functors.ClosureTransformer:48","type":"CtIfImpl"},"type":"adrStmt","transplantationPoint":{"sourceCode":"org.apache.commons.collections4.Closure<? super T>.execute(T)","position":"org.apache.commons.collections4.functors.ClosureTransformer:72","type":"CtInvocationImpl"},"status":0},{"failures":[],"variableMapping":{},"name":"addReaction","transplant":{"sourceCode":"java.util.Iterator<? extends E> = null","position":"org.apache.commons.collections4.iterators.ObjectGraphIterator:249","type":"CtAssignmentImpl"},"type":"adrStmt","transplantationPoint":{"sourceCode":"this.java.util.Iterator<? extends E> = ((java.util.Iterator<? extends E>)(E))","position":"org.apache.commons.collections4.iterators.ObjectGraphIterator:109","type":"CtAssignmentImpl"},"status":0},{"failures":[],"variableMapping":{},"name":"replaceWittgenstein","transplant":{"sourceCode":"boolean = true","position":"org.apache.commons.collections4.iterators.ReverseListIterator:108","type":"CtAssignmentImpl"},"type":"adrStmt","transplantationPoint":{"sourceCode":"if ((boolean) == false) {\r\n    throw new java.lang.IllegalStateException(\"Cannot add to list until next() or previous() called\");\r\n} ","position":"org.apache.commons.collections4.iterators.ReverseListIterator:158","type":"CtIfImpl"},"status":0},{"failures":[],"variableMapping":{},"name":"addRandom","transplant":{"sourceCode":"if (java.util.AbstractMap<K, V>.isEmpty()) {\r\n    return null;\r\n} ","position":"org.apache.commons.collections4.trie.AbstractPatriciaTrie:748","type":"CtIfImpl"},"type":"adrStmt","transplantationPoint":{"sourceCode":"org.apache.commons.collections4.bag.TreeBag<E>.getMap()","position":"org.apache.commons.collections4.bag.TreeBag:96","type":"CtInvocationImpl"},"status":0}],"failedTests":[],"id":35,"status":0}