{"transformations":[{"failures":[],"variableMapping":{},"name":"replaceWittgenstein","transplant":{"sourceCode":"return true","position":"org.apache.commons.collections4.iterators.FilterListIterator:236","type":"CtReturnImpl"},"type":"adrStmt","transplantationPoint":{"sourceCode":"return org.apache.commons.collections4.map.SingletonMap<K, V>.(isEqualKey(java.util.Map.Entry<?, ?>.getKey())) && org.apache.commons.collections4.map.SingletonMap<K, V>.(isEqualValue(java.util.Map.Entry<?, ?>.getValue()))","position":"org.apache.commons.collections4.map.SingletonMap:546","type":"CtReturnImpl"},"status":0},{"failures":[],"variableMapping":{},"name":"addRandom","transplant":{"sourceCode":"org.apache.commons.collections4.bidimap.AbstractOrderedBidiMapDecorator<K, V>.decorated()","position":"org.apache.commons.collections4.bidimap.AbstractOrderedBidiMapDecorator:68","type":"CtInvocationImpl"},"type":"adrStmt","transplantationPoint":{"sourceCode":"boolean = true","position":"org.apache.commons.collections4.list.GrowthList:155","type":"CtAssignmentImpl"},"status":0},{"failures":[],"variableMapping":{"list":"list"},"name":"add","transplant":{"sourceCode":"if (java.util.List<E> == null) {\r\n    throw new java.lang.IllegalArgumentException(\"List must not be null\");\r\n} ","position":"org.apache.commons.collections4.list.SetUniqueList:72","type":"CtIfImpl"},"type":"adrStmt","transplantationPoint":{"sourceCode":"if (java.util.List<E>.isEmpty()) {\r\n    throw new java.util.NoSuchElementException(\"There are no elements for this iterator to loop on\");\r\n} ","position":"org.apache.commons.collections4.iterators.LoopingListIterator:140","type":"CtIfImpl"},"status":0},{"failures":[],"variableMapping":{},"name":"replace","transplant":{"sourceCode":"return \"[]\"","position":"org.apache.commons.collections4.bag.AbstractMapBag:585","type":"CtReturnImpl"},"type":"adrStmt","transplantationPoint":{"sourceCode":"return org.apache.commons.collections4.map.AbstractMapDecorator<K, V>.decorated().toString()","position":"org.apache.commons.collections4.map.AbstractMapDecorator:140","type":"CtReturnImpl"},"status":0},{"failures":[],"variableMapping":{"key":"lock"},"name":"add","transplant":{"sourceCode":"if (java.lang.Object == null) {\r\n    return 0;\r\n} ","position":"org.apache.commons.collections4.map.StaticBucketMap:154","type":"CtIfImpl"},"type":"adrStmt","transplantationPoint":{"sourceCode":"synchronized(java.lang.Object) {\r\n    return org.apache.commons.collections4.collection.SynchronizedCollection<E>.decorated().hashCode();\r\n}","position":"org.apache.commons.collections4.collection.SynchronizedCollection:204","type":"CtSynchronizedImpl"},"status":0}],"failedTests":[],"id":33,"status":0}