{"transformations":[{"failures":[],"variableMapping":{},"name":"replace","transplant":{"sourceCode":"int int = 0","position":"org.apache.commons.collections4.bag.AbstractMapBag:568","type":"CtLocalVariableImpl"},"type":"adrStmt","transplantationPoint":{"sourceCode":"final int int = org.apache.commons.collections4.list.AbstractListDecorator<E>.decorated().size()","position":"org.apache.commons.collections4.list.GrowthList:151","type":"CtLocalVariableImpl"},"status":0},{"failures":[],"variableMapping":{"currentIndex":"iCount"},"name":"add","transplant":{"sourceCode":"if ((int) == (-1)) {\r\n    throw new java.lang.IllegalStateException();\r\n} ","position":"org.apache.commons.collections4.list.TreeList:1093","type":"CtIfImpl"},"type":"adrStmt","transplantationPoint":{"sourceCode":"for (int int = 0 ; int < (int) ; int++) {\r\n    org.apache.commons.collections4.Closure<? super E>.execute(E);\r\n}","position":"org.apache.commons.collections4.functors.ForClosure:80","type":"CtForImpl"},"status":0},{"failures":[],"name":"delete","type":"adrStmt","transplantationPoint":{"sourceCode":"throw new java.lang.NullPointerException(\"The list must not be null\")","position":"org.apache.commons.collections4.iterators.LoopingListIterator:59","type":"CtThrowImpl"},"status":0},{"failures":[],"variableMapping":{},"name":"replaceWittgenstein","transplant":{"sourceCode":"return false","position":"org.apache.commons.collections4.iterators.FilterListIterator:239","type":"CtReturnImpl"},"type":"adrStmt","transplantationPoint":{"sourceCode":"return org.apache.commons.collections4.list.AbstractLinkedList.LinkedListIterator<E>.(previousIndex()) >= 0","position":"org.apache.commons.collections4.list.AbstractLinkedList:911","type":"CtReturnImpl"},"status":0},{"failures":[],"variableMapping":{},"name":"replaceRandom","transplant":{"sourceCode":"org.apache.commons.collections4.map.AbstractHashedMap<K, V>.clear()","position":"org.apache.commons.collections4.map.AbstractReferenceMap:294","type":"CtInvocationImpl"},"type":"adrStmt","transplantationPoint":{"sourceCode":"java.io.ObjectOutputStream.defaultWriteObject()","position":"org.apache.commons.collections4.bag.TreeBag:117","type":"CtInvocationImpl"},"status":0}],"failedTests":[],"id":52,"status":-1}